[
    {
        "URL": "https://www.unegui.mn/new-buildings/114-shine-ih-tojruu-hothon/",
        "Price": "169.96 сая ₮ – 442.88 сая ₮",
        "Area": "4 сая ₮/м²",
        "Title": "ШИНЭ ИХ ТОЙРУУ хотхон",
        "Location": "Not found",
        "Rooms": "2 өрөө",
        "Posted Date": "Not found",
        "Ad Number": "114",
        "Balcony": "Not found",
        "Window": "Not found",
        "Year of Completion": "Not found",
        "Garage": "Not found",
        "Building Floors": "Not found",
        "Door": "Not found",
        "Floor Number": "Not found",
        "Number of Windows": "Not found",
        "Elevator": "Not found",
        "Construction Status": "Not found",
        "Payment Terms": "Not found",
        "Description": "Not found"
    },
    {
        "URL": "https://www.unegui.mn/new-buildings/20-mandah-naran-hothon/",
        "Price": "180.44 сая ₮ – 569.04 сая ₮",
        "Area": "4 сая ₮/м²",
        "Title": "Мандах Наран Хотхон",
        "Location": "Улаанбаатар хот, Хан-Уул дүүрэг 15-р хороо, Махатма ганди гудамж, Галакси тауэр 801тоот",
        "Rooms": "3 өрөө",
        "Posted Date": "Not found",
        "Ad Number": "20",
        "Balcony": "Not found",
        "Window": "Not found",
        "Year of Completion": "Not found",
        "Garage": "Not found",
        "Building Floors": "Not found",
        "Door": "Not found",
        "Floor Number": "Not found",
        "Number of Windows": "Not found",
        "Elevator": "Not found",
        "Construction Status": "Not found",
        "Payment Terms": "Not found",
        "Description": "Not found"
    },
    {
        "URL": "https://www.unegui.mn/new-buildings/2-hleg-residens-hothon/",
        "Price": "144 сая ₮ – 249.6 сая ₮",
        "Area": "3.2 сая ₮/м²",
        "Title": "Хүлэг Ресидэнс Хотхон",
        "Location": "Улаанбаатар, Хан-Уул, Арцатын ам",
        "Rooms": "Улаанбаатар хотын шинэ суурьшлын бүс Хан-Уул дүүрэг Арцатын аманд шинэ төлөвлөлт, орчин цагийн барилгын өнгө төрхийг тодорхойлсон бүтээн байгуулалт эхлүүлээд явж байгаа, \"KHULEG RESIDENCE\" төслийн хамт олноос та бүхэндээ мэндчилж байна. Архитекторын шийдэл 16-н давхар орон сууцыг төлөвлөхдөө зоорийн давхарт авто зогсоол, 1 давхартаа үйлчилгээ 2-16 дугаар давхартаа 7 айлтай орон сууц төлөвлөсөн. Уг барилгын хийцлэл нь төмөр бетон бүтээцтэй, нийт 5 блок орон сууц, авто грашнаас бүрдэнэ. В, С блок нь 16.5х35.0м, D, E блок нь 22.5х44.5м хэмжээтэй. Барилгын нүүр талыг орчны барилга байгууламжтай уялдуулан цагаан болон саарал өнгийн эмулсээр хийхээр төлөвлөсөн. Дотор өрөөний төлөвлөлтийг байгаль цаг уурын нөхцөл, захиалагчийн хүсэлт болон тав тухыг бодолцон төлөвлөв. Гадна тохижилт нь хүүхдийн тоглоомын талбай, явган хүн, авто зогсоолын хэсгээс бүрдэнэ. Тоглоомын талбайг авто замын хөдөлгөөнөөс тусад нь төлөвлөн галын аюулын үед хэрэглэгдэх туслах замыг төлөвлөж өгсөн.",
        "Posted Date": "Not found",
        "Ad Number": "16",
        "Balcony": "Not found",
        "Window": "Not found",
        "Year of Completion": "Not found",
        "Garage": "Not found",
        "Building Floors": "Not found",
        "Door": "Not found",
        "Floor Number": "Not found",
        "Number of Windows": "Not found",
        "Elevator": "Not found",
        "Construction Status": "Not found",
        "Payment Terms": "Not found",
        "Description": "Not found"
    }
]